true_north/__init__.py
true_north/__main__.py
true_north/_check.py
true_north/_cli.py
true_north/_colors.py
true_north/_config.py
true_north/_group.py
true_north/py.typed
true_north/types.py
true_north/_loopers/__init__.py
true_north/_loopers/_common.py
true_north/_loopers/_each.py
true_north/_loopers/_memory.py
true_north/_loopers/_opcode.py
true_north/_loopers/_total.py
true_north/_results/__init__.py
true_north/_results/_base.py
true_north/_results/_formatters.py
true_north/_results/_malloc.py
true_north/_results/_opcodes.py
true_north/_results/_timing.py
true_north-0.3.0.dist-info/entry_points.txt
true_north-0.3.0.dist-info/LICENSE
true_north-0.3.0.dist-info/WHEEL
true_north-0.3.0.dist-info/METADATA
true_north-0.3.0.dist-info/RECORD
