Metadata-Version: 2.1
Name: true-north
Version: 0.3.0
Summary: Beautiful and pythonic benchmarks engine.
Keywords: benchmark,benchmarks,performance,profiling,testing,tests
Author-email: Gram <git@orsinium.dev>
Requires-Python: >=3.8
Classifier: Development Status :: 5 - Production/Stable
Classifier: Intended Audience :: Developers
Classifier: License :: OSI Approved :: MIT License
Classifier: Programming Language :: Python
Classifier: Typing :: Typed
Requires-Dist: sphinx ; extra == "docs"
Requires-Dist: myst-parser ; extra == "docs"
Requires-Dist: isort ; extra == "lint"
Requires-Dist: flake8 ; extra == "lint"
Requires-Dist: unify ; extra == "lint"
Requires-Dist: mypy ; extra == "lint"
Requires-Dist: pytest ; extra == "test"
Requires-Dist: pytest-cov ; extra == "test"
Project-URL: Source, https://github.com/orsinium-labs/true-north
Provides-Extra: docs
Provides-Extra: lint
Provides-Extra: test
